unofficial_livecounts_api/__init__.py
unofficial_livecounts_api/env.py
unofficial_livecounts_api/error.py
unofficial_livecounts_api/tiktok.py
unofficial_livecounts_api/twitch.py
unofficial_livecounts_api/twitter.py
unofficial_livecounts_api/utils.py
unofficial_livecounts_api/youtube.py
unofficial_livecounts_api-0.1.6.dist-info/LICENSE
unofficial_livecounts_api-0.1.6.dist-info/METADATA
unofficial_livecounts_api-0.1.6.dist-info/WHEEL
unofficial_livecounts_api-0.1.6.dist-info/RECORD
