Metadata-Version: 2.1
Name: unofficial-livecounts-api
Version: 0.1.6
Summary: Unofficial API Livecounts.io
Author: Jonas
Author-email: me@ifelse.one
Requires-Python: >=3.10,<4.0
Classifier: Programming Language :: Python :: 3
Classifier: Programming Language :: Python :: 3.10
Classifier: Programming Language :: Python :: 3.11
Classifier: Programming Language :: Python :: 3.12
Classifier: Programming Language :: Python :: 3.13
Requires-Dist: latest-user-agents (>=0.0.4,<0.0.5)
Requires-Dist: pycryptodome (>=3.20.0,<4.0.0)
Requires-Dist: python-dotenv (>=1.0.1,<2.0.0)
Requires-Dist: urllib3 (>=2.2.2,<3.0.0)
Requires-Dist: validators (>=0.34.0,<0.35.0)
